async_db_polars/__init__.py
async_db_polars/db.py
async_db_polars/pgdb.py
async_db_polars-0.1.8.dist-info/METADATA
async_db_polars-0.1.8.dist-info/WHEEL
async_db_polars-0.1.8.dist-info/RECORD
